ou_tm351_py/__init__.py
ou_tm351_py-0.0.11.dist-info/LICENSE
ou_tm351_py-0.0.11.dist-info/METADATA
ou_tm351_py-0.0.11.dist-info/WHEEL
ou_tm351_py-0.0.11.dist-info/top_level.txt
ou_tm351_py-0.0.11.dist-info/RECORD
